{
 "pair": "ind",
 "sources": [
  "ud",
  "unimorph",
  "wiktionary",
  "unfoldingword"
 ],
 "stats": {
  "pos_words": 58415,
  "pos_verified": 9024,
  "pos_conflicts": 2155,
  "lexemes": 3591,
  "wordforms": 6261,
  "unimorph_pairs": 27714,
  "affixes": 44,
  "glosses": 3410,
  "key_terms": 953,
  "homographs": 715,
  "inflection_classes": 5,
  "lemmas_classed": 1083,
  "lemmas_regular": 785,
  "aligned_glosses_filled": 198,
  "aligned_names_added": 173,
  "scripture_vocab": 6984,
  "scripture_attested": 6261,
  "scripture_coverage": 0.8965,
  "scripture_uncovered": 696
 },
 "destination": "LibLCM / FieldWorks HC: LexEntry(+MoMorphType) · MoStemMsa/MoInflAffMsa(PartOfSpeech+FsFeatStruc) · AffixTemplate",
 "writing_system": {
  "locale": "id-ID",
  "group": [
   ".",
   " ",
   " "
  ],
  "decimal": ",",
  "style": "european",
  "numerals": "token type (not HC-parsed)",
  "punctuation": "stripped at tokenization"
 },
 "token_classes": {
  "word": 6957,
  "number": 27
 },
 "files": [
  "lexicon.jsonl",
  "lexicon.lift",
  "inflection_classes.jsonl",
  "wordforms.jsonl",
  "grammar_rules.jsonl",
  "phonology.jsonl",
  "key_terms.jsonl",
  "meta.json",
  "golden_scripture.tsv"
 ],
 "pos_conflicts_sample": [
  [
   "taksonomi",
   "Proper noun",
   "Noun"
  ],
  [
   "kara",
   "Proper noun",
   "Noun"
  ],
  [
   "kilat",
   "Verb",
   "Noun"
  ],
  [
   "qrs",
   "Proper noun",
   "Noun"
  ],
  [
   "los",
   "Proper noun",
   "Noun"
  ],
  [
   "sebaya",
   "Adjective",
   "Noun"
  ],
  [
   "giur",
   "Verb",
   "Adjective"
  ],
  [
   "senapati",
   "Proper noun",
   "Noun"
  ],
  [
   "awatara",
   "Proper noun",
   "Noun"
  ],
  [
   "orde",
   "Proper noun",
   "Verb",
   "Noun"
  ],
  [
   "kw",
   "Proper noun",
   "Noun"
  ],
  [
   "y",
   "Proper noun",
   "Interjection"
  ],
  [
   "serbuk",
   "Verb",
   "Noun"
  ],
  [
   "hatta",
   "Proper noun",
   "Adverb"
  ],
  [
   "gusti",
   "Proper noun",
   "Noun"
  ],
  [
   "garuda",
   "Proper noun",
   "Noun"
  ],
  [
   "representasi",
   "Verb",
   "Noun"
  ],
  [
   "kayak",
   "Verb",
   "Adposition"
  ],
  [
   "adati",
   "Verb",
   "Adjective"
  ],
  [
   "sidi",
   "Proper noun",
   "Adjective"
  ],
  [
   "rugi",
   "Adjective",
   "Verb",
   "Noun"
  ],
  [
   "arsir",
   "Noun",
   "Verb"
  ],
  [
   "sana",
   "Pronoun",
   "Verb",
   "Adverb"
  ],
  [
   "mutiara",
   "Proper noun",
   "Noun"
  ],
  [
   "pascapanen",
   "Noun",
   "Adjective"
  ],
  [
   "betul-betul",
   "Adjective",
   "Adverb"
  ],
  [
   "liput",
   "Verb",
   "Noun"
  ],
  [
   "seandainya",
   "Subordinating connective",
   "Coordinating connective"
  ],
  [
   "ob",
   "Proper noun",
   "Noun"
  ],
  [
   "kecurian",
   "Noun",
   "Verb"
  ],
  [
   "karena",
   "Subordinating connective",
   "Coordinating connective"
  ],
  [
   "ulas",
   "Verb",
   "Noun"
  ],
  [
   "parit",
   "Verb",
   "Noun"
  ],
  [
   "licik",
   "Adjective",
   "Noun"
  ],
  [
   "gengsi",
   "Verb",
   "Noun"
  ],
  [
   "junior",
   "Noun",
   "Adjective"
  ],
  [
   "wedana",
   "Proper noun",
   "Noun"
  ],
  [
   "punuk",
   "Verb",
   "Noun"
  ],
  [
   "tri",
   "Proper noun",
   "Numeral"
  ],
  [
   "spiritual",
   "Noun",
   "Adjective"
  ]
 ],
 "scripture_uncovered_sample": [
  "aakn",
  "aalah",
  "abadon",
  "abaraham",
  "abilene",
  "abiud",
  "abyatar",
  "achaia",
  "adramitium",
  "adria",
  "afia",
  "ahaz",
  "ainon",
  "ajabi",
  "akaikus",
  "akana",
  "akeldama",
  "akim",
  "alabaster",
  "aleksandar",
  "aleksandira",
  "aleksandria",
  "aling",
  "allahdan",
  "allaku",
  "amana",
  "amen",
  "amfipolis",
  "amon",
  "ampliatus",
  "ampunilah",
  "andronikus",
  "antipatris",
  "apeles",
  "apius",
  "apolion",
  "apsintus",
  "arfaksad",
  "arkelaus",
  "armageddon"
 ]
}